<changelogs>
	<changelog>
		<element>com_cgresa</element>
		<type>component</type>
		<version>2.4.0</version>
        <note>
            <item>Update : 04/03/2025</item>
        </note>
        <fix>
            <item>Joomla 5.3 compatibility : getQuery to createQuery</item>
        </fix>
	</changelog>
	<changelog>
		<element>com_cgresa</element>
		<type>component</type>
		<version>2.3.6</version>
        <note>
            <item>Update : 24/02/2025</item>
        </note>
        <fix>
            <item>PHP 8.4 compatibility</item>
            <item>Install script  : missing delete function</item>
        </fix>
	</changelog>
	<changelog>
		<element>com_cgresa</element>
		<type>component</type>
		<version>2.3.5</version>
        <note>
            <item>Update : 08/11/2023</item>
        </note>
        <fix>
            <item>Suppress PHP warnings</item>
            <item>Missing phone/size check in form validator</item>
			<item>Delete unnecessary files</item>
        </fix>
	</changelog>
	<changelog>
		<element>com_cgresa</element>
		<type>component</type>
		<version>2.3.4</version>
        <note>
            <item>Update : 06/11/2023</item>
        </note>
        <fix>
            <item>Undefined constant "ConseilGouzComponentCGResaSiteControlleremail" </item>
        </fix>
	</changelog>
	<changelog>
		<element>com_cgresa</element>
		<type>component</type>
		<version>2.3.3</version>
        <note>
            <item>Update : 07/09/2023</item>
        </note>
        <fix>
            <item>PHP 8.2 : deprecated function utf8_encode</item>
			<item>handle empty eventlist in TimepickRule </item>
        </fix>
	</changelog>
	<changelog>
		<element>com_cgresa</element>
		<type>component</type>
		<version>2.3.2</version>
        <note>
            <item>Update : 07/09/2023</item>
        </note>
        <fix>
            <item>Table : remove protected params; line</item>
			<item>Fix CSS Admin</item>
        </fix>
		<addition>
			<item>Automatic version number from xml file</item>
		</addition>
	</changelog>
	<changelog>
		<element>com_cgresa</element>
		<type>component</type>
		<version>2.3.1</version>
        <note>
            <item>Update : 02/09/2023</item>
        </note>
        <addition>
            <item>Add minimum party size parameter</item>
        </addition>
	</changelog>
	<changelog>
		<element>com_cgresa</element>
		<type>component</type>
		<version>2.3.0</version>
        <note>
            <item>Update : 20/07/2023</item>
        </note>
        <fix>
            <item>Joomla 5.x compatibility</item>
        </fix>
	</changelog>
	<changelog>
		<element>com_cgresa</element>
		<type>component</type>
		<version>2.2.6</version>
        <note>
            <item>Update : 12/03/2023</item>
        </note>
        <fix>
            <item>Fix admin CSS</item>
        </fix>
	</changelog>
	<changelog>
		<element>com_cgresa</element>
		<type>component</type>
		<version>2.2.5</version>
        <note>
            <item>Update : 12/03/2023</item>
        </note>
        <fix>
            <item>wrong version number displayed</item>
        </fix>
	</changelog>
	<changelog>
		<element>com_cgresa</element>
		<type>component</type>
		<version>2.2.4</version>
        <note>
            <item>Update : 12/03/2023</item>
        </note>
        <addition>
            <item>Implement Inline Help</item>
			<item>Updates/changelog on github</item>
        </addition>
	</changelog>
	<changelog>
		<element>com_cgresa</element>
		<type>component</type>
		<version>2.2.3</version>
        <note>
            <item>Update : 11/04/2022</item>
        </note>
        <fix>
            <item>JText error</item>
        </fix>
	</changelog>
	<changelog>
		<element>com_cgresa</element>
		<type>component</type>
		<version>2.2.2</version>
        <note>
            <item>Update : 08/04/2022</item>
        </note>
        <fix>
            <item>wrong time format</item>
        </fix>
	</changelog>
	<changelog>
		<element>com_cgresa</element>
		<type>component</type>
		<version>2.1.3</version>
        <note>
            <item>Update : 21/12/2021</item>
        </note>
        <addition>
            <item>Phoca collapse compatibility</item>
        </addition>
	</changelog>
	<changelog>
		<element>com_cgresa</element>
		<type>component</type>
		<version>2.1.2</version>
        <note>
            <item>Update : 19/12/2021</item>
        </note>
        <fix>
            <item>replace timepicker</item>
        </fix>
	</changelog>
	<changelog>
		<element>com_cgresa</element>
		<type>component</type>
		<version>2.1.1</version>
        <note>
            <item>Update : 16/12/2021</item>
        </note>
        <fix>
            <item>replace boostrap tab by uitab</item>
        </fix>
	</changelog>
	<changelog>
		<element>com_cgresa</element>
		<type>component</type>
		<version>2.2.3</version>
        <note>
            <item>Update : 06/12/2021</item>
        </note>
        <fix>
            <item>Evénements peandant les congès</item>
        </fix>
	</changelog>
	<changelog>
		<element>com_cgresa</element>
		<type>component</type>
		<version>2.0.9</version>
        <note>
            <item>Update : 25/11/2021</item>
        </note>
        <fix>
            <item>SEF URL</item>
        </fix>
	</changelog>
	<changelog>
		<element>com_cgresa</element>
		<type>component</type>
		<version>2.0.8</version>
        <note>
            <item>Update : 05/11/2021</item>
        </note>
        <fix>
            <item>params access error</item>
        </fix>
	</changelog>
	<changelog>
		<element>com_cgresa</element>
		<type>component</type>
		<version>2.0.7</version>
        <note>
            <item>Update : 30/10/2021</item>
        </note>
        <fix>
            <item>script install error</item>
        </fix>
        <fix>
            <item>Missing html tags in comments</item>
        </fix>
	</changelog>
	<changelog>
		<element>com_cgresa</element>
		<type>component</type>
		<version>2.0.6</version>
        <note>
            <item>Update : 29/10/2021</item>
        </note>
        <fix>
            <item>thankyou.php error</item>
        </fix>
        <fix>
            <item>Missing html tags in comments</item>
        </fix>
	</changelog>
	<changelog>
		<element>com_cgresa</element>
		<type>component</type>
		<version>2.0.5</version>
        <note>
            <item>Update : 14/10/2021</item>
        </note>
        <fix>
            <item>error on menu updates in script.php</item>
        </fix>
        <fix>
            <item>Missing html tags in comments</item>
        </fix>
	</changelog>
	<changelog>
		<element>com_cgresa</element>
		<type>component</type>
		<version>2.0.4</version>
        <note>
            <item>Update : 07/10/2021</item>
        </note>
        <addition>
            <item>Cleanup old version via script.php</item>
        </addition>
	</changelog>
	<changelog>
		<element>com_cgresa</element>
		<type>component</type>
		<version>2.0.3</version>
        <note>
            <item>Update : 16/09/2021</item>
        </note>
        <change>
            <item>Wrong layout file for TextresaField</item>
        </change>
	</changelog>
	<changelog>
		<element>com_cgresa</element>
		<type>component</type>
		<version>2.0.2</version>
        <note>
            <item>Update : 14/09/2021</item>
        </note>
        <change>
            <item>Wrong version number</item>
        </change>
	</changelog>
	<changelog>
		<element>com_cgresa</element>
		<type>component</type>
		<version>2.0.1</version>
        <note>
            <item>Update : 14/09/2021</item>
        </note>
        <change>
            <item>Closing days</item>
        </change>
	</changelog>
	<changelog>
		<element>com_cgisotope</element>
		<type>component</type>
		<version>2.0.0</version>
        <note>
            <item>Update : 11/07/2021</item>
        </note>
        <addition>
            <item>Joomla 4.0 compatibility</item>
        </addition>
	</changelog>
</changelogs>
